AUTh_authenticator/__init__.py
AUTh_authenticator/__preHeaders__.py
AUTh_authenticator/universis.py
AUTh_authenticator-0.5.0.dist-info/LICENSE
AUTh_authenticator-0.5.0.dist-info/METADATA
AUTh_authenticator-0.5.0.dist-info/WHEEL
AUTh_authenticator-0.5.0.dist-info/top_level.txt
AUTh_authenticator-0.5.0.dist-info/RECORD
